{
  "mcpServers": {
    "chkp-mcp-servers": {
      "command": "uvx",
      "args": [
        "--from",
        "git+https://github.com/mkol5222/chkp_mcps",
        "chkp-mcp-servers-mcp-server"
      ],
      "metadata": {
        "name": "CheckPoint MCP Servers Explorer",
        "description": "MCP server for exploring and introspecting CheckPoint MCP servers",
        "version": "0.1.4",
        "author": "Martin Koldovsky",
        "repository": "https://github.com/mkol5222/chkp_mcps"
      }
    }
  }
}
